odoo/addons/l10n_es_reav/README.rst
odoo/addons/l10n_es_reav/__init__.py
odoo/addons/l10n_es_reav/__manifest__.py
odoo/addons/l10n_es_reav/data/template/account.fiscal.position-es_common.csv
odoo/addons/l10n_es_reav/data/template/account.tax-es_common.csv
odoo/addons/l10n_es_reav/data/template/account.tax.group-es_common.csv
odoo/addons/l10n_es_reav/i18n/es.po
odoo/addons/l10n_es_reav/i18n/l10n_es_reav.pot
odoo/addons/l10n_es_reav/models/__init__.py
odoo/addons/l10n_es_reav/models/account_chart_template.py
odoo/addons/l10n_es_reav/readme/CONFIGURE.md
odoo/addons/l10n_es_reav/readme/CONTRIBUTORS.md
odoo/addons/l10n_es_reav/readme/DESCRIPTION.md
odoo/addons/l10n_es_reav/readme/USAGE.md
odoo/addons/l10n_es_reav/static/description/icon.png
odoo/addons/l10n_es_reav/static/description/index.html
odoo_addon_l10n_es_reav-17.0.1.0.0.3.dist-info/METADATA
odoo_addon_l10n_es_reav-17.0.1.0.0.3.dist-info/WHEEL
odoo_addon_l10n_es_reav-17.0.1.0.0.3.dist-info/top_level.txt
odoo_addon_l10n_es_reav-17.0.1.0.0.3.dist-info/RECORD
