Metadata-Version: 2.1
Name: odoo-addon-l10n_es_reav
Version: 17.0.1.0.0.3
Requires-Python: >=3.10
Requires-Dist: odoo>=17.0a,<17.1dev
Summary: =?utf-8?q?REAV_-_R=C3=A9gimen_Especial_Agencias_de_Viajes?=
Home-page: https://github.com/OCA/l10n-spain
License: AGPL-3
Author: Bilbonet, Odoo Community Association (OCA)
Author-email: support@odoo-community.org
Classifier: Programming Language :: Python
Classifier: Framework :: Odoo
Classifier: Framework :: Odoo :: 17.0
Classifier: License :: OSI Approved :: GNU Affero General Public License v3
